{
	"animations": [
		{
			"loop": false,
			"offsets": [
				0,
				0
			],
			"anim": "idle",
			"fps": 12,
			"name": "fang idle",
			"indices": []
		},
		{
			"loop": false,
			"offsets": [
				0,
				-9
			],
			"anim": "singDOWN",
			"fps": 12,
			"name": "fang down",
			"indices": []
		},
		{
			"loop": false,
			"offsets": [
				-3,
				-10
			],
			"anim": "singUP",
			"fps": 12,
			"name": "fang up",
			"indices": []
		},
		{
			"loop": false,
			"offsets": [
				1,
				-12
			],
			"anim": "singLEFT",
			"fps": 12,
			"name": "fang left",
			"indices": []
		},
		{
			"loop": false,
			"offsets": [
				0,
				-9
			],
			"anim": "singRIGHT",
			"fps": 12,
			"name": "fang right",
			"indices": []
		}
	],
	"no_antialiasing": false,
	"image": "characters/fang",
	"position": [
		0,
		-210
	],
	"healthicon": "fang",
	"flip_x": false,
	"healthbar_colors": [
		0,
		152,
		255
	],
	"camera_position": [
		0,
		0
	],
	"sing_duration": 6.1,
	"scale": 1
}